request_api_builder/__init__.py
request_api_builder/rab.py
request_api_builder/utils.py
request_api_builder-2.1.1.dist-info/METADATA
request_api_builder-2.1.1.dist-info/WHEEL
request_api_builder-2.1.1.dist-info/licenses/LICENSE
request_api_builder-2.1.1.dist-info/RECORD
