Metadata-Version: 2.3
Name: request_api_builder
Version: 2.1.1
Summary: Request builder for testing API
Author-email: Kateryna Levashova <voxquietam.md@gmail.com>
License-File: LICENSE
Classifier: License :: OSI Approved :: MIT License
Classifier: Operating System :: OS Independent
Classifier: Programming Language :: Python :: 3
Requires-Python: >=3.10.0
